myy_functions
