Metadata-Version: 1.0
Name: myy-functions
Version: 0.0.2
Summary: Snowflake function
Home-page: UNKNOWN
Author: UNKNOWN
Author-email: UNKNOWN
License: UNKNOWN
Platform: UNKNOWN
